/*
 * To change this license header, choose License Headers in Project Properties.
 * To change this template file, choose Tools | Templates
 * and open the template in the editor.
 */
package sdf.controller;
import sdf.model.Hotel;

/**
 *
 * @author muthu
 */

public class HotelController extends Controller {
    
    public HotelController() {
        // <editor-fold defaultstate="collapsed" desc="Compiled Code">
        /* 0: aload_0
         * 1: invokespecial sdf/controller/Controller."<init>":()V
         * 4: return
         *  */
        // </editor-fold>
    }

    public void addHotel(Hotel ptnt) {
        // <editor-fold defaultstate="collapsed" desc="Compiled Code">
        /* 0: aload_0
         * 1: invokevirtual sdf/controller/PatientController.getModel:()Lsdf/model/Model;
         * 4: checkcast     sdf/model/PatientList
         * 7: astore_2
         * 8: aload_2
         * 9: aload_1
         * 10: invokevirtual sdf/model/PatientList.add:(Lsdf/model/Patient;)V
         * 13: return
         *  */
        // </editor-fold>
    }
}
    

